mycalc/calculator.py
acme31-0.0.1.dist-info/METADATA
acme31-0.0.1.dist-info/WHEEL
acme31-0.0.1.dist-info/top_level.txt
acme31-0.0.1.dist-info/RECORD
