Metadata-Version: 2.1
Name: acme31
Version: 0.0.1
Summary: nice calculator
Home-page: https://github.com/acme31/calc0001
Download-URL: https://github.com.sejin-chun/calc0001/archive/refs/tags/v0.0.1.zip
Author: LeeMinJun
License: UNKNOWN
Platform: UNKNOWN
Classifier: Programming Language :: Python :: 3
Classifier: Operating System :: OS Independent
